epanetmsx/__init__.py
epanetmsx/_toolkit.so
epanetmsx/toolkit.py
epanetmsx/libmsxcore.so
epanetmsx-2.0.0.dist-info/WHEEL
epanetmsx-2.0.0.dist-info/top_level.txt
epanetmsx-2.0.0.dist-info/METADATA
epanetmsx-2.0.0.dist-info/LICENSE
epanetmsx-2.0.0.dist-info/RECORD
epanetmsx.libs/libgomp-f7e03b3e.so.1.0.0
