Metadata-Version: 2.1
Name: epanetmsx
Version: 2.0.0
Summary: A thin wrapper for epanet-msx toolkit
Home-page: https://github.com/karrowood/epanet-msx-python
Author: Kyle Arrowood
Author-email: kyle.a.arrowood@gmail.com
License: UNKNOWN
Platform: UNKNOWN
